epgm_model/EPGM.py
epgm_model/__init__.py
epgm_model/utils.py
epgm_model-0.1.1.dist-info/METADATA
epgm_model-0.1.1.dist-info/WHEEL
epgm_model-0.1.1.dist-info/top_level.txt
epgm_model-0.1.1.dist-info/RECORD
