Metadata-Version: 2.1
Name: epgm_model
Version: 0.1.1
Summary: Implementation of the EPGM model for time series forecasting.
Author: Haris Masood
Author-email: haris_masood@yahoo.com
License: MIT
Classifier: Development Status :: 5 - Production/Stable
Classifier: Intended Audience :: Financial and Insurance Industry
Classifier: Programming Language :: Python :: 3
Classifier: Topic :: Office/Business :: Financial
Requires-Dist: numpy
Requires-Dist: scikit-learn
Requires-Dist: pandas
Requires-Dist: matplotlib
Requires-Dist: scipy
